meta_llama_3_yarn/__init__.py
meta_llama_3_yarn/configuration_llama.py
meta_llama_3_yarn/modeling_llama.py
meta_llama_3_yarn-0.1.3.dist-info/LICENSE
meta_llama_3_yarn-0.1.3.dist-info/METADATA
meta_llama_3_yarn-0.1.3.dist-info/WHEEL
meta_llama_3_yarn-0.1.3.dist-info/top_level.txt
meta_llama_3_yarn-0.1.3.dist-info/RECORD
