Metadata-Version: 2.1
Name: meta-llama-3-yarn
Version: 0.1.3
Summary: YaRN Implementation compatible with HuggingFace Transformers
Home-page: https://github.com/MeetKai/meta-llama-3-yarn
Author: Jeffrey Fong
Author-email: jeffrey.fong@meetkai.com
License-File: LICENSE
Requires-Dist: transformers ==4.41.2
